MANIFEST.in
README.rst
setup.cfg
setup.py
versioneer.py
dataframe_sql/__init__.py
dataframe_sql/_version.py
dataframe_sql/sql_select_query.py
dataframe_sql.egg-info/PKG-INFO
dataframe_sql.egg-info/SOURCES.txt
dataframe_sql.egg-info/dependency_links.txt
dataframe_sql.egg-info/requires.txt
dataframe_sql.egg-info/top_level.txt
dataframe_sql/tests/__init__.py
dataframe_sql/tests/markers.py
dataframe_sql/tests/pandas_sql_functionality_test.py
dataframe_sql/tests/performance_tests.py
dataframe_sql/tests/utils.py